rls/__init__.py
rls/alembic_rls.py
rls/create_policies.py
rls/principals.py
rls/register_rls.py
rls/rls_session.py
rls/rls_sessioner.py
rls/schemas.py
rls-0.3.0.dist-info/LICENSE
rls-0.3.0.dist-info/METADATA
rls-0.3.0.dist-info/WHEEL
rls-0.3.0.dist-info/RECORD
