Metadata-Version: 2.1
Name: rls
Version: 0.3.0
Summary: fastapi sqlalchemy rls integration package
License: MIT
Author: DelfinaCare
Author-email: open-source@delfina.com
Requires-Python: >=3.11
Classifier: License :: OSI Approved :: MIT License
Classifier: Programming Language :: Python :: 3
Classifier: Programming Language :: Python :: 3.11
Classifier: Programming Language :: Python :: 3.12
Requires-Dist: annotated-types (==0.7.0)
Requires-Dist: anyio (==4.4.0)
Requires-Dist: asyncpg (>=0.29.0,<0.30.0)
Requires-Dist: fastapi (==0.114.2)
Requires-Dist: greenlet (==3.1.0)
Requires-Dist: idna (==3.10)
Requires-Dist: once-py (>=0.0.6,<0.0.7)
Requires-Dist: psycopg2 (==2.9.9)
Requires-Dist: pydantic (==2.9.1)
Requires-Dist: pydantic-core (==2.23.3)
Requires-Dist: sniffio (==1.3.1)
Requires-Dist: sqlalchemy (==2.0.34)
Requires-Dist: starlette (==0.38.5)
Requires-Dist: typing-extensions (==4.12.2)
